reclaim/__init__.py
reclaim/__main__.py
reclaim/parse.py
reclaim/str.py
reclaim/utils.py
reclaim/commands/__init__.py
reclaim/commands/add-time.py
reclaim/commands/base.py
reclaim/commands/create-task.py
reclaim/commands/delete-task.py
reclaim/commands/edit-task.py
reclaim/commands/list-tasks.py
reclaim/commands/log-work.py
reclaim/commands/mark-task.py
reclaim/commands/show-load.py
reclaim/commands/show-task.py
reclaim/commands/start-task.py
reclaim/commands/stop-task.py
reclaim_cli-0.1.4.dist-info/licenses/LICENSE
reclaim_cli-0.1.4.dist-info/METADATA
reclaim_cli-0.1.4.dist-info/WHEEL
reclaim_cli-0.1.4.dist-info/entry_points.txt
reclaim_cli-0.1.4.dist-info/top_level.txt
reclaim_cli-0.1.4.dist-info/RECORD
