Metadata-Version: 2.4
Name: reclaim-cli
Version: 0.1.4
Summary: A command-line tool for interacting with Reclaim.ai for task management.
Author-email: Rieck <konrad@mlsec.org>
License: MIT
Project-URL: Homepage, https://github.com/rieck/reclaim-cli
Project-URL: Source, https://github.com/rieck/reclaim-cli
Project-URL: Issues, https://github.com/rieck/reclaim-cli/issues
Project-URL: Changelog, https://github.com/rieck/reclaim-cli/blob/main/CHANGELOG.md
Keywords: cli,reclaim,productivity,automation
Classifier: Programming Language :: Python :: 3
Classifier: Programming Language :: Python :: 3.10
Classifier: Programming Language :: Python :: 3.11
Classifier: License :: OSI Approved :: MIT License
Classifier: Operating System :: OS Independent
Classifier: Environment :: Console
Classifier: Intended Audience :: End Users/Desktop
Classifier: Topic :: Utilities
Classifier: Topic :: Office/Business :: Scheduling
Requires-Python: >=3.10
License-File: LICENSE
Requires-Dist: PyYAML>=6.0
Requires-Dist: dateparser==1.2.1
Requires-Dist: rich==13.9.4
Requires-Dist: reclaim-sdk==0.6.4
Provides-Extra: dev
Requires-Dist: pytest; extra == "dev"
Requires-Dist: pytest-cov; extra == "dev"
Requires-Dist: black; extra == "dev"
Requires-Dist: isort; extra == "dev"
Requires-Dist: pre-commit; extra == "dev"
Requires-Dist: flake8; extra == "dev"
Requires-Dist: flake8-docstrings; extra == "dev"
Requires-Dist: flake8-bugbear; extra == "dev"
Requires-Dist: flake8-quotes; extra == "dev"
Dynamic: license-file
